dingtalk/__init__.py
dingtalk/dingtalk.py
dingtalk_webhook-1.1.6.dist-info/METADATA
dingtalk_webhook-1.1.6.dist-info/WHEEL
dingtalk_webhook-1.1.6.dist-info/top_level.txt
dingtalk_webhook-1.1.6.dist-info/RECORD
