Metadata-Version: 2.1
Name: dingtalk-webhook
Version: 1.1.6
Summary: send dingtalk message to dingding webhook robot
Home-page: https://github.com/x-hezhang/dingtalk-webhook
Author: zhanghe
Author-email: x_hezhang@126.com
License: GNU GPLv3
Keywords: dingtalk,dingding,dingtalk-webhook,ding,alert
Platform: UNKNOWN
